ontology/__init__.py
ontology-0.1.0.dist-info/METADATA
ontology-0.1.0.dist-info/WHEEL
ontology-0.1.0.dist-info/top_level.txt
ontology-0.1.0.dist-info/RECORD
