Metadata-Version: 2.1
Name: ontology
Version: 0.1.0
Summary: Ontology Library
Author-email: Kevin <kevinqz@gmail.com>
Requires-Python: >=3.11
